[[{"left":0,"value":"<!DOCTYPE"},{"left":10,"value":"html>"}],[{"left":0,"value":"<html>"}],[{"left":2,"value":"<head>"}],[{"left":4,"value":"<title>"},{"left":11,"value":"Hi"},{"left":14,"value":"there!"},{"left":20,"value":"<\/title>"}],[{"left":4,"value":"<link"},{"left":10,"value":"rel="},{"left":14,"value":"\"stylesheet\""},{"left":27,"value":"href="},{"left":32,"value":"\"default.css\""},{"left":46,"value":"\/>"}],[{"left":2,"value":"<\/head>"}],[{"left":2,"value":"<body"},{"left":8,"value":"style="},{"left":14,"value":"\"background-image:url(sheet.jpg)\">"}],[{"left":4,"value":"<h1>"},{"left":8,"value":"Magnetic"},{"left":17,"value":"HTML"},{"left":21,"value":"&trade;"},{"left":28,"value":"<\/h1>"}],[{"left":4,"value":"<h2>"},{"left":8,"value":"Get"},{"left":12,"value":"the"},{"left":16,"value":"real-life"},{"left":26,"value":"version"},{"left":34,"value":"for"},{"left":38,"value":"your"},{"left":43,"value":"fridge!"},{"left":50,"value":"<\/h2>"}],[{"left":4,"value":"<div"},{"left":9,"value":"class="},{"left":15,"value":"\"buttons"},{"left":24,"value":"full-widths\""},{"left":36,"value":">"}],[{"left":6,"value":"<a"},{"left":9,"value":"class="},{"left":15,"value":"\"primary\""},{"left":25,"value":"href="},{"left":30,"value":"\"http:\/\/amzn.to\/1G66iB5\""},{"left":55,"value":"target="},{"left":62,"value":"\"_blank\""},{"left":70,"value":">"},{"left":71,"value":"$10"},{"left":75,"value":"with"},{"left":80,"value":"Amazon"},{"left":87,"value":"Prime"},{"left":92,"value":"<\/a>"}],[{"left":6,"value":"<a"},{"left":9,"value":"class="},{"left":15,"value":"\"primary\""},{"left":25,"value":"href="},{"left":30,"value":"\"http:\/\/robertakarobin.com\""},{"left":58,"value":"target="},{"left":65,"value":"\"_blank\""},{"left":73,"value":">"},{"left":74,"value":"hello@RobertAKARobin.com"},{"left":98,"value":"<\/a>"}],[{"left":4,"value":"<\/div>"}],[{"left":2,"value":"<\/body>"}],[{"left":0,"value":"<\/html>"}],[]]